ContactExtractor/ContactExtractor.py
ContactExtractor/LICENSE
ContactExtractor/README.md
ContactExtractor/__init__.py
ContactExtractor/examples/1ffk_0_kt7.cif
ContactExtractor/examples/2fmt.pdb
ContactExtractor/examples/3d2g_A_kj.cif
contactextractor-1.0.0.dist-info/METADATA
contactextractor-1.0.0.dist-info/WHEEL
contactextractor-1.0.0.dist-info/entry_points.txt
contactextractor-1.0.0.dist-info/licenses/LICENSE
contactextractor-1.0.0.dist-info/RECORD
