Metadata-Version: 2.4
Name: ContactExtractor
Version: 1.0.0
Summary: Contact Extractor from PDB/mmCIF coordinate files
Project-URL: Homepage, https://github.com/febos/ContExt
Project-URL: Issues, https://github.com/febos/ContExt/issues
Author-email: "Eugene F. Baulin" <efbaulin@gmail.com>
Maintainer-email: "Eugene F. Baulin" <efbaulin@gmail.com>
License-File: LICENSE
Classifier: Operating System :: OS Independent
Classifier: Programming Language :: Python :: 3
Classifier: Topic :: Scientific/Engineering :: Bio-Informatics
Requires-Python: >=3.8
Requires-Dist: scipy
